moonshine/BUILD
moonshine/__init__.py
moonshine/models/BUILD
moonshine/models/__init__.py
moonshine/models/base.py
moonshine/models/logging.py
moonshine/models/model_parameters.py
moonshine/models/unet.py
moonshine/models/unet_test.py
moonshine/preprocessing/BUILD
moonshine/preprocessing/__init__.py
moonshine/preprocessing/preprocess.py
moonshine/preprocessing/preprocess_test.py
moonshine/preprocessing/settings.py
moonshine-0.1.7.dist-info/METADATA
moonshine-0.1.7.dist-info/WHEEL
moonshine-0.1.7.dist-info/licenses/LICENSE
moonshine-0.1.7.dist-info/RECORD
