Metadata-Version: 2.1
Name: moonshine
Version: 0.1.7
Summary: Pretrained remote sensing models.
Project-URL: Homepage, https://github.com/moonshinelabs/moonshine
Author-email: Nate Harada <moonshine@moonshinelabs.ai>
License: MIT
License-File: LICENSE
Keywords: moonshine,remote,satellite,sensing
Classifier: License :: OSI Approved :: MIT License
Classifier: Programming Language :: Python :: 3
Requires-Python: >=3.7
Requires-Dist: segmentation-models-pytorch==0.3.2
Requires-Dist: smart-open[s3]==6.3.0
